be/__init__.py
be/__main__.py
be/_autocomplete.sh
be/_data.py
be/_extern.py
be/_shell.bat
be/_shell.sh
be/api.py
be/cli.py
be/lib.py
be/util.py
be/version.py
be/vendor/__init__.py
be/vendor/click/__init__.py
be/vendor/click/_bashcomplete.py
be/vendor/click/_compat.py
be/vendor/click/_termui_impl.py
be/vendor/click/_textwrap.py
be/vendor/click/core.py
be/vendor/click/decorators.py
be/vendor/click/exceptions.py
be/vendor/click/formatting.py
be/vendor/click/parser.py
be/vendor/click/termui.py
be/vendor/click/testing.py
be/vendor/click/types.py
be/vendor/click/utils.py
be/vendor/requests/__init__.py
be/vendor/requests/adapters.py
be/vendor/requests/api.py
be/vendor/requests/auth.py
be/vendor/requests/cacert.pem
be/vendor/requests/certs.py
be/vendor/requests/compat.py
be/vendor/requests/cookies.py
be/vendor/requests/exceptions.py
be/vendor/requests/hooks.py
be/vendor/requests/models.py
be/vendor/requests/sessions.py
be/vendor/requests/status_codes.py
be/vendor/requests/structures.py
be/vendor/requests/utils.py
be/vendor/requests/packages/__init__.py
be/vendor/requests/packages/chardet/__init__.py
be/vendor/requests/packages/chardet/big5freq.py
be/vendor/requests/packages/chardet/big5prober.py
be/vendor/requests/packages/chardet/chardetect.py
be/vendor/requests/packages/chardet/chardistribution.py
be/vendor/requests/packages/chardet/charsetgroupprober.py
be/vendor/requests/packages/chardet/charsetprober.py
be/vendor/requests/packages/chardet/codingstatemachine.py
be/vendor/requests/packages/chardet/compat.py
be/vendor/requests/packages/chardet/constants.py
be/vendor/requests/packages/chardet/cp949prober.py
be/vendor/requests/packages/chardet/escprober.py
be/vendor/requests/packages/chardet/escsm.py
be/vendor/requests/packages/chardet/eucjpprober.py
be/vendor/requests/packages/chardet/euckrfreq.py
be/vendor/requests/packages/chardet/euckrprober.py
be/vendor/requests/packages/chardet/euctwfreq.py
be-0.3.8.dist-info/METADATA
be-0.3.8.dist-info/RECORD
be-0.3.8.dist-info/WHEEL
be-0.3.8.dist-info/entry_points.txt
be-0.3.8.dist-info/top_level.txt
