Metadata-Version: 2.1
Name: be
Version: 0.3.8
Summary: Minimal asset management system
Home-page: https://github.com/mottosso/be
Author: Abstract Factory
Author-email: marcus@abstractfactory.com
License: LGPLv2.1
Platform: UNKNOWN
Classifier: Development Status :: 3 - Alpha
Classifier: Intended Audience :: Developers
Classifier: License :: OSI Approved :: GNU Lesser General Public License v3 (LGPLv3)
Classifier: Programming Language :: Python
Classifier: Programming Language :: Python :: 2
Classifier: Programming Language :: Python :: 2.6
Classifier: Programming Language :: Python :: 2.7
Classifier: Topic :: Software Development :: Libraries :: Python Modules
Classifier: Topic :: Utilities
Requires-Dist: psutil (==2.2.1)
